pbn2html/__init__.py
pbn2html/all_template.html
pbn2html/auction_template.html
pbn2html/deal_template.html
pbn2html/game_state.py
pbn2html/output.pbn
pbn2html/pbn2html.py
pbn2html/pbn_parser.py
pbn2html/template.html
pbn2html-0.0.28.dist-info/LICENSE
pbn2html-0.0.28.dist-info/METADATA
pbn2html-0.0.28.dist-info/WHEEL
pbn2html-0.0.28.dist-info/entry_points.txt
pbn2html-0.0.28.dist-info/top_level.txt
pbn2html-0.0.28.dist-info/RECORD
