Metadata-Version: 2.1
Name: pbn2html
Version: 0.0.28
Summary: converter from pbn files to html
Home-page: https://github.com/larrycai/pbn2html
Author: Larry Cai
Author-email: larry.caiyu@gmail.com
License: UNKNOWN
Platform: UNKNOWN
Classifier: Programming Language :: Python :: 3
Classifier: License :: OSI Approved :: MIT License
Classifier: Operating System :: OS Independent
Requires-Python: >=3.6
